<?xml version="1.0" ?>
<CHARACTER>
	<TEXTURES>
		<texture filePath="assets/droid_zapper/run.png" textureID="droid_zapper_run"/>
		<texture filePath="assets/droid_zapper/wake.png" textureID="droid_zapper_wake"/>
		<texture filePath="assets/droid_zapper/none.png" textureID="droid_zapper_none"/>
		<texture filePath="assets/droid_zapper/attack.png" textureID="droid_zapper_attack1"/>
		<texture filePath="assets/droid_zapper/damaged.png" textureID="droid_zapper_hit"/>
		<texture filePath="assets/droid_zapper/death.png" textureID="droid_zapper_death"/>
	</TEXTURES>
	<ACTIONS>
		<action name="run" textureID="droid_zapper_run" numFrame="6" w="190" h="64"/>
		<action name="none" textureID="droid_zapper_none" numFrame="1" w="190" h="64"/>
		<action name="wake" textureID="droid_zapper_wake" numFrame="7" w="190" h="64" speed="2"/>
		<action name="attack1" textureID="droid_zapper_attack1" numFrame="10" w="190" h="64" speed="2"/>
		<action name="dying" textureID="droid_zapper_death" numFrame="8" w="190" h="64" speed="2"/>
		<action name="hit" textureID="droid_zapper_hit" numFrame="2" w="190" h="64" speed="2"/>
	</ACTIONS>
</CHARACTER>